mafio/__init__.py
mafio/reader.py
mafio/writer.py
mafio-1.0.2.dist-info/LICENSE
mafio-1.0.2.dist-info/METADATA
mafio-1.0.2.dist-info/WHEEL
mafio-1.0.2.dist-info/top_level.txt
mafio-1.0.2.dist-info/RECORD
