Metadata-Version: 2.1
Name: mafio
Version: 1.0.2
Summary: A package for maf files io
Home-page: https://github.com/zeyad-kay/mafio
Author: Zeyad Khaled
License: UNKNOWN
Project-URL: Bug Tracker, https://github.com/zeyad-kay/mafio/issues
Platform: UNKNOWN
Classifier: Programming Language :: Python :: 3
Classifier: License :: OSI Approved :: MIT License
Classifier: Operating System :: OS Independent
License-File: LICENSE
